circuit/__init__.py
circuit/circuit.py
circuit-2.0.1.dist-info/LICENSE
circuit-2.0.1.dist-info/METADATA
circuit-2.0.1.dist-info/WHEEL
circuit-2.0.1.dist-info/top_level.txt
circuit-2.0.1.dist-info/RECORD
